{"records": [{"name": "kiddy", "time": 4855, "date": "2015-08-15T20:32:30.000Z", "rank": 1}, {"name": "d3lt4_07", "time": 4991, "date": "2015-09-05T19:07:43.000Z", "rank": 2}, {"name": "Quebo", "time": 5000, "date": "2015-08-15T18:42:52.000Z", "rank": 3}, {"name": "The_Unknown", "time": 5104, "date": "2015-09-05T08:45:40.000Z", "rank": 4}, {"name": "Lakitu", "time": 5179, "date": "2015-09-21T12:37:23.000Z", "rank": 5}, {"name": "Air_runner", "time": 5246, "date": "2015-08-15T18:21:50.000Z", "rank": 6}, {"name": "OneFive", "time": 5293, "date": "2015-08-14T22:04:01.000Z", "rank": 7}, {"name": "kanzo", "time": 5471, "date": "2015-09-02T15:59:02.000Z", "rank": 8}, {"name": "xXApathyXx", "time": 5649, "date": "2015-08-15T18:21:50.000Z", "rank": 9}, {"name": "benje", "time": 5668, "date": "2015-08-27T16:52:01.000Z", "rank": 10}, {"name": "lillipeo", "time": 5809, "date": "2015-08-27T16:30:00.000Z", "rank": 11}, {"name": "Grrrdian", "time": 5889, "date": "2014-01-25T14:55:00.000Z", "rank": 12}, {"name": "Personal_Best", "time": 5899, "date": "2015-09-19T19:31:21.000Z", "rank": 13}, {"name": "anymal", "time": 5976, "date": "2015-09-05T19:07:43.000Z", "rank": 14}, {"name": "itsTxrnz", "time": 6017, "date": "2015-09-16T19:04:02.000Z", "rank": 15}, {"name": "e1348391", "time": 6826, "date": "2015-08-31T08:07:47.000Z", "rank": 16}, {"name": "Per4karta", "time": 6901, "date": "2015-09-04T11:11:09.000Z", "rank": 17}, {"name": "_Lags_", "time": 6973, "date": "2015-09-15T16:16:43.000Z", "rank": 18}, {"name": "suppengabel", "time": 6994, "date": "2015-09-02T17:52:58.000Z", "rank": 19}, {"name": "sploosh", "time": 7471, "date": "2014-07-26T07:45:01.000Z", "rank": 20}, {"name": "mazaa", "time": 7533, "date": "2014-01-25T04:51:00.000Z", "rank": 21}, {"name": "hawkks", "time": 7541, "date": "2015-09-25T23:19:39.000Z", "rank": 22}, {"name": "solit0n", "time": 7601, "date": "2014-05-31T23:42:00.000Z", "rank": 23}, {"name": "Fuldas", "time": 7659, "date": "2015-08-27T19:41:32.000Z", "rank": 24}, {"name": "am1go", "time": 7664, "date": "2015-08-27T19:41:32.000Z", "rank": 25}, {"name": "KoMyHHa", "time": 7799, "date": "2015-09-05T20:02:23.000Z", "rank": 26}, {"name": "illidan", "time": 7968, "date": "2014-01-25T14:55:00.000Z", "rank": 27}, {"name": "fella", "time": 8136, "date": "2015-08-27T15:35:34.000Z", "rank": 28}, {"name": "Vibration", "time": 8159, "date": "2014-05-15T05:30:34.000Z", "rank": 29}, {"name": "Svensland", "time": 8279, "date": "2015-09-06T15:44:50.000Z", "rank": 30}, {"name": "w_w", "time": 8411, "date": "2015-08-14T22:04:01.000Z", "rank": 31}, {"name": "andrasrx8", "time": 8450, "date": "2015-09-05T11:44:13.000Z", "rank": 32}, {"name": "Her0c", "time": 8505, "date": "2015-08-15T00:18:00.000Z", "rank": 33}, {"name": "Uhuru", "time": 8528, "date": "2015-09-02T15:59:02.000Z", "rank": 34}, {"name": "paparas", "time": 8551, "date": "2015-09-19T17:40:46.000Z", "rank": 35}, {"name": "eLeMeNt", "time": 8572, "date": "2014-01-25T14:55:00.000Z", "rank": 36}, {"name": "Er1ca", "time": 8700, "date": "2014-06-03T21:13:00.000Z", "rank": 37}, {"name": "ivanZor", "time": 8936, "date": "2015-09-19T17:40:46.000Z", "rank": 38}, {"name": "RhumPomPomPom", "time": 8964, "date": "2015-09-06T15:44:50.000Z", "rank": 39}, {"name": "l3fty", "time": 9014, "date": "2015-09-02T17:52:58.000Z", "rank": 40}, {"name": "Joga_Bonito", "time": 9034, "date": "2015-09-10T06:33:28.000Z", "rank": 41}, {"name": "TwinScrew", "time": 9583, "date": "2014-07-26T07:45:01.000Z", "rank": 42}, {"name": "Turkey", "time": 9973, "date": "2015-09-05T19:07:43.000Z", "rank": 43}, {"name": "anders2809", "time": 10055, "date": "2015-08-14T22:04:01.000Z", "rank": 44}, {"name": "muffin", "time": 10074, "date": "2014-01-25T14:46:00.000Z", "rank": 45}, {"name": "Nevakeee", "time": 10680, "date": "2015-09-04T05:03:32.000Z", "rank": 46}, {"name": "spieldy", "time": 11191, "date": "2014-01-25T04:51:00.000Z", "rank": 47}, {"name": "voodoo_maniac", "time": 11338, "date": "2015-08-27T16:52:01.000Z", "rank": 48}, {"name": "Ivymad_", "time": 11440, "date": "2015-09-05T08:45:40.000Z", "rank": 49}, {"name": "Phoenix", "time": 11571, "date": "2014-06-03T21:13:00.000Z", "rank": 50}, {"name": "dtavi", "time": 11632, "date": "2015-08-31T08:07:47.000Z", "rank": 51}, {"name": "Momentum", "time": 11841, "date": "2014-07-26T07:45:01.000Z", "rank": 52}, {"name": "vXo666", "time": 11957, "date": "2015-09-02T17:52:58.000Z", "rank": 53}, {"name": "Thibma", "time": 12590, "date": "2015-09-06T11:46:44.000Z", "rank": 54}, {"name": "Deltzu", "time": 12723, "date": "2015-08-27T16:30:00.000Z", "rank": 55}, {"name": "kliurka", "time": 13303, "date": "2015-09-02T17:52:58.000Z", "rank": 56}, {"name": "feitan_san", "time": 13604, "date": "2015-09-15T16:55:58.000Z", "rank": 57}, {"name": "Sentium", "time": 13718, "date": "2015-09-15T16:55:58.000Z", "rank": 58}, {"name": "yourhighnesss", "time": 14690, "date": "2015-09-06T13:59:41.000Z", "rank": 59}, {"name": "shiit", "time": 15243, "date": "2015-08-27T16:30:00.000Z", "rank": 60}, {"name": "Zita", "time": 16905, "date": "2015-08-15T20:09:41.000Z", "rank": 61}, {"name": "barada", "time": 26207, "date": "2015-08-27T15:35:34.000Z", "rank": 62}, {"name": "herrfrau", "time": 146072, "date": "2015-08-14T22:04:01.000Z", "rank": 63}]}