{"records": [{"rank": 1, "name": "Lakitu", "date": "2014-07-06T19:56:31.000Z", "time": 8235}, {"rank": 2, "name": "JustQuake", "date": "2014-03-11T15:04:00.000Z", "time": 8358}, {"rank": 3, "name": "w_w", "date": "2014-04-10T14:04:00.000Z", "time": 8600}, {"rank": 4, "name": "wichtL", "date": "2014-02-25T13:06:00.000Z", "time": 8606}, {"rank": 5, "name": "desfsd", "date": "2014-02-24T18:34:00.000Z", "time": 8608}, {"rank": 6, "name": "EmSixTeen", "date": "2014-02-23T13:14:00.000Z", "time": 8737}, {"rank": 7, "name": "HOX", "date": "2014-02-01T12:55:00.000Z", "time": 8830}, {"rank": 8, "name": "JDB_", "date": "2014-07-01T23:42:40.000Z", "time": 8909}, {"rank": 9, "name": "G4rlock", "date": "2014-02-25T09:41:00.000Z", "time": 9005}, {"rank": 10, "name": "Exkalibur", "date": "2014-03-01T03:00:00.000Z", "time": 9038}, {"rank": 11, "name": "xXApathyXx", "date": "2014-08-04T23:31:10.000Z", "time": 9039}, {"rank": 12, "name": "nons", "date": "2014-02-08T09:39:00.000Z", "time": 9041}, {"rank": 13, "name": "hawkks", "date": "2014-04-13T15:14:00.000Z", "time": 9050}, {"rank": 14, "name": "pietroo", "date": "2014-08-07T16:58:07.000Z", "time": 9076}, {"rank": 15, "name": "jcb", "date": "2014-01-29T15:10:00.000Z", "time": 9098}, {"rank": 16, "name": "toaney", "date": "2014-06-30T01:50:56.000Z", "time": 9129}, {"rank": 17, "name": "kanzo", "date": "2014-02-14T05:42:00.000Z", "time": 9183}, {"rank": 18, "name": "ZoOt", "date": "2014-07-07T00:44:15.000Z", "time": 9196}, {"rank": 19, "name": "D4rkFl4sh", "date": "2014-06-26T20:07:57.000Z", "time": 9222}, {"rank": 20, "name": "zelaya", "date": "2014-08-23T23:18:44.000Z", "time": 9239}, {"rank": 21, "name": "CraShiq", "date": "2014-01-29T15:10:00.000Z", "time": 9341}, {"rank": 22, "name": "lzelayal", "date": "2014-08-24T10:24:32.000Z", "time": 9359}, {"rank": 23, "name": "ret4ks", "date": "2014-08-07T16:40:04.000Z", "time": 9366}, {"rank": 24, "name": "WaterWolf", "date": "2014-06-08T13:02:08.000Z", "time": 9406}, {"rank": 25, "name": "gnosis", "date": "2014-04-20T08:08:00.000Z", "time": 9409}, {"rank": 26, "name": "LeoSko", "date": "2014-08-24T11:10:36.000Z", "time": 9426}, {"rank": 27, "name": "fraggedICE", "date": "2014-01-09T20:58:00.000Z", "time": 9487}, {"rank": 28, "name": "MadHatman", "date": "2014-07-06T19:56:31.000Z", "time": 9509}, {"rank": 29, "name": "Dezerter", "date": "2014-06-18T13:04:42.000Z", "time": 9510}, {"rank": 30, "name": "blaqsaqattaq", "date": "2014-03-02T16:56:00.000Z", "time": 9537}, {"rank": 31, "name": "godzuki", "date": "2014-03-05T22:41:00.000Z", "time": 9551}, {"rank": 32, "name": "gamba", "date": "2014-07-09T13:27:52.000Z", "time": 9554}, {"rank": 33, "name": "frixio", "date": "2014-08-06T08:10:16.000Z", "time": 9569}, {"rank": 34, "name": "cast", "date": "2014-03-03T16:04:00.000Z", "time": 9573}, {"rank": 35, "name": "5hr00m", "date": "2014-08-07T14:40:26.000Z", "time": 9576}, {"rank": 36, "name": "keiZ", "date": "2014-04-24T23:11:00.000Z", "time": 9593}, {"rank": 37, "name": "terg", "date": "2014-08-07T16:40:04.000Z", "time": 9615}, {"rank": 38, "name": "Shintaz", "date": "2014-04-18T14:32:00.000Z", "time": 9623}, {"rank": 39, "name": "Persp3ct1ve", "date": "2014-08-08T03:07:06.000Z", "time": 9665}, {"rank": 40, "name": "humster", "date": "2014-08-14T14:42:30.000Z", "time": 9676}, {"rank": 41, "name": "REDEMPTOR", "date": "2014-02-24T10:42:00.000Z", "time": 9761}, {"rank": 42, "name": "d3sp3r", "date": "2014-08-24T10:24:32.000Z", "time": 9820}, {"rank": 43, "name": "orsy", "date": "2014-08-06T19:51:41.000Z", "time": 9828}, {"rank": 43, "name": "187pure", "date": "2014-08-07T14:40:26.000Z", "time": 9828}, {"rank": 45, "name": "no7sag", "date": "2014-07-28T20:31:16.000Z", "time": 9847}, {"rank": 46, "name": "Jey", "date": "2014-08-17T19:36:46.000Z", "time": 9859}, {"rank": 47, "name": "Gamblez", "date": "2014-08-07T16:31:02.000Z", "time": 9965}, {"rank": 48, "name": "sploosh", "date": "2014-08-11T02:45:56.000Z", "time": 9968}, {"rank": 49, "name": "TerribleTrioJon", "date": "2014-08-08T03:07:06.000Z", "time": 9971}, {"rank": 50, "name": "tommmmm", "date": "2014-02-22T13:36:00.000Z", "time": 9987}, {"rank": 51, "name": "smok1e", "date": "2014-02-21T05:24:00.000Z", "time": 10020}, {"rank": 52, "name": "Anhyzr", "date": "2014-02-16T02:51:00.000Z", "time": 10052}, {"rank": 53, "name": "Anhedonic", "date": "2014-02-14T05:42:00.000Z", "time": 10064}, {"rank": 54, "name": "Tranqualizer", "date": "2014-03-01T03:00:00.000Z", "time": 10074}, {"rank": 55, "name": "Str1ng", "date": "2014-04-20T08:08:00.000Z", "time": 10116}, {"rank": 56, "name": "Tichi", "date": "2014-06-06T02:12:18.000Z", "time": 10157}, {"rank": 57, "name": "MrOllie", "date": "2014-08-02T00:25:29.000Z", "time": 10163}, {"rank": 58, "name": "Taffy", "date": "2014-06-14T00:52:30.000Z", "time": 10175}, {"rank": 59, "name": "koolaid22", "date": "2014-08-11T02:45:56.000Z", "time": 10201}, {"rank": 60, "name": "COLE_PIPER", "date": "2014-08-09T20:20:59.000Z", "time": 10202}, {"rank": 61, "name": "rpL", "date": "2014-02-12T10:04:00.000Z", "time": 10235}, {"rank": 62, "name": "MadDream", "date": "2014-01-06T02:28:00.000Z", "time": 10248}, {"rank": 63, "name": "NewName", "date": "2013-12-27T17:07:00.000Z", "time": 10303}, {"rank": 64, "name": "Feomathari", "date": "2014-08-07T16:58:07.000Z", "time": 10323}, {"rank": 65, "name": "van1IIa", "date": "2014-06-26T20:07:57.000Z", "time": 10325}, {"rank": 66, "name": "SouLMatE", "date": "2014-04-07T07:48:00.000Z", "time": 10367}, {"rank": 67, "name": "Gush", "date": "2014-07-06T20:15:15.000Z", "time": 10384}, {"rank": 68, "name": "magicfruits", "date": "2014-06-01T14:47:00.000Z", "time": 10396}, {"rank": 69, "name": "kashis", "date": "2014-06-25T19:15:30.000Z", "time": 10404}, {"rank": 70, "name": "Phekda", "date": "2014-08-17T18:24:29.000Z", "time": 10411}, {"rank": 71, "name": "PaCmanPL", "date": "2014-02-12T12:28:00.000Z", "time": 10414}, {"rank": 72, "name": "Zar", "date": "2014-01-12T13:47:00.000Z", "time": 10422}, {"rank": 73, "name": "N_Tropy_", "date": "2014-04-13T14:32:00.000Z", "time": 10441}, {"rank": 74, "name": "Krinzen", "date": "2014-03-02T16:56:00.000Z", "time": 10445}, {"rank": 75, "name": "Quebo", "date": "2014-08-17T18:24:29.000Z", "time": 10473}, {"rank": 76, "name": "Kasadeem", "date": "2014-07-05T02:17:31.000Z", "time": 10474}, {"rank": 77, "name": "Brejk", "date": "2013-12-28T14:23:00.000Z", "time": 10595}, {"rank": 78, "name": "secondary", "date": "2014-06-09T15:09:53.000Z", "time": 10655}, {"rank": 78, "name": "ntt", "date": "2014-08-06T19:51:41.000Z", "time": 10655}, {"rank": 80, "name": "cobrask", "date": "2014-06-25T19:15:30.000Z", "time": 10666}, {"rank": 81, "name": "wohy", "date": "2014-05-18T20:55:44.000Z", "time": 10685}, {"rank": 82, "name": "ZORD0N", "date": "2014-06-09T07:51:57.000Z", "time": 10688}, {"rank": 83, "name": "NitroMen", "date": "2013-12-18T01:37:00.000Z", "time": 10694}, {"rank": 84, "name": "Vixterra", "date": "2014-02-16T02:51:00.000Z", "time": 10709}, {"rank": 85, "name": "WWWWWWWWWWW", "date": "2014-08-18T04:03:05.000Z", "time": 10715}, {"rank": 86, "name": "Wh1t3r_r", "date": "2014-01-25T12:10:00.000Z", "time": 10771}, {"rank": 87, "name": "Raymon", "date": "2014-03-30T06:09:00.000Z", "time": 10772}, {"rank": 88, "name": "Fawwles", "date": "2014-03-30T06:09:00.000Z", "time": 10801}, {"rank": 89, "name": "SARK", "date": "2014-08-14T16:30:55.000Z", "time": 10836}, {"rank": 90, "name": "Z0nd3r", "date": "2014-08-06T19:51:41.000Z", "time": 10848}, {"rank": 91, "name": "Dark_Eden", "date": "2014-04-16T13:28:00.000Z", "time": 10880}, {"rank": 92, "name": "balas", "date": "2014-05-18T13:52:06.000Z", "time": 10887}, {"rank": 93, "name": "faith_Tom", "date": "2014-08-14T20:06:34.000Z", "time": 10916}, {"rank": 94, "name": "Lorfa", "date": "2014-08-14T02:21:02.000Z", "time": 10918}, {"rank": 95, "name": "Dmitriy", "date": "2014-08-17T20:49:15.000Z", "time": 10948}, {"rank": 96, "name": "zkrzk", "date": "2014-04-16T13:28:00.000Z", "time": 10973}, {"rank": 97, "name": "TwininGss", "date": "2014-06-09T07:51:57.000Z", "time": 11001}, {"rank": 98, "name": "takkomatto", "date": "2014-08-24T10:24:32.000Z", "time": 11008}, {"rank": 99, "name": "istwo", "date": "2014-05-18T13:52:06.000Z", "time": 11036}, {"rank": 100, "name": "charlychad", "date": "2014-04-20T08:08:00.000Z", "time": 11049}, {"rank": 101, "name": "Tekenre", "date": "2014-05-18T13:52:06.000Z", "time": 11066}, {"rank": 102, "name": "ownedbyrock", "date": "2014-08-06T19:51:41.000Z", "time": 11095}, {"rank": 103, "name": "tr1ce", "date": "2014-04-18T14:32:00.000Z", "time": 11101}, {"rank": 104, "name": "am1wo", "date": "2014-02-13T10:59:00.000Z", "time": 11143}, {"rank": 105, "name": "DaveArbiter", "date": "2014-03-22T11:20:00.000Z", "time": 11144}, {"rank": 106, "name": "eLeMeNt", "date": "2014-06-14T00:52:30.000Z", "time": 11148}, {"rank": 107, "name": "Latvietis", "date": "2014-01-28T10:00:00.000Z", "time": 11155}, {"rank": 108, "name": "noob9", "date": "2014-08-07T05:44:44.000Z", "time": 11159}, {"rank": 109, "name": "bion1c", "date": "2014-07-28T20:31:16.000Z", "time": 11160}, {"rank": 110, "name": "Overdese", "date": "2014-04-02T03:56:00.000Z", "time": 11162}, {"rank": 111, "name": "egorkez", "date": "2014-01-19T04:58:00.000Z", "time": 11167}, {"rank": 112, "name": "Briggzy", "date": "2014-08-18T04:03:05.000Z", "time": 11216}, {"rank": 113, "name": "Goro92", "date": "2014-08-13T07:39:41.000Z", "time": 11222}, {"rank": 114, "name": "FlyingOrodrake", "date": "2014-08-06T19:51:41.000Z", "time": 11251}, {"rank": 115, "name": "ErAxY", "date": "2014-01-27T07:02:00.000Z", "time": 11272}, {"rank": 116, "name": "Hilly", "date": "2014-06-23T16:21:36.000Z", "time": 11300}, {"rank": 117, "name": "jas390", "date": "2013-12-23T01:57:00.000Z", "time": 11301}, {"rank": 118, "name": "1ee", "date": "2014-02-21T13:39:00.000Z", "time": 11308}, {"rank": 119, "name": "verz", "date": "2014-08-19T17:24:26.000Z", "time": 11352}, {"rank": 120, "name": "BilboBagins", "date": "2014-02-13T05:18:00.000Z", "time": 11383}, {"rank": 121, "name": "_time", "date": "2014-05-18T13:43:05.000Z", "time": 11393}, {"rank": 122, "name": "Swyfty", "date": "2014-07-05T02:01:57.000Z", "time": 11403}, {"rank": 123, "name": "atwa", "date": "2014-05-29T16:36:00.000Z", "time": 11411}, {"rank": 124, "name": "kukufz", "date": "2014-06-09T00:38:09.000Z", "time": 11447}, {"rank": 125, "name": "Recursion", "date": "2014-08-06T17:25:46.000Z", "time": 11457}, {"rank": 126, "name": "DaNoNo", "date": "2014-04-24T23:11:00.000Z", "time": 11476}, {"rank": 127, "name": "ChrisDakota", "date": "2014-08-07T14:49:28.000Z", "time": 11499}, {"rank": 128, "name": "Evolu7ion", "date": "2014-06-26T20:07:57.000Z", "time": 11516}, {"rank": 129, "name": "p3l3", "date": "2014-08-07T16:49:05.000Z", "time": 11556}, {"rank": 130, "name": "electriic", "date": "2014-05-10T06:13:31.000Z", "time": 11657}, {"rank": 131, "name": "Stalker72", "date": "2014-02-22T06:48:00.000Z", "time": 11690}, {"rank": 132, "name": "MicFragger", "date": "2014-08-24T11:10:36.000Z", "time": 11697}, {"rank": 133, "name": "Scroxe", "date": "2014-04-07T07:48:00.000Z", "time": 11717}, {"rank": 134, "name": "spieldy", "date": "2014-01-09T20:58:00.000Z", "time": 11732}, {"rank": 135, "name": "sarco", "date": "2014-08-23T23:18:44.000Z", "time": 11733}, {"rank": 136, "name": "muckster", "date": "2014-04-16T13:28:00.000Z", "time": 11764}, {"rank": 137, "name": "gKoLT", "date": "2014-04-09T17:05:00.000Z", "time": 11790}, {"rank": 138, "name": "mrgamezombie", "date": "2014-06-01T14:47:00.000Z", "time": 11820}, {"rank": 139, "name": "Instar", "date": "2014-08-14T11:26:19.000Z", "time": 11833}, {"rank": 140, "name": "Des1gn", "date": "2014-05-29T16:36:00.000Z", "time": 11851}, {"rank": 141, "name": "777terraastroix", "date": "2014-08-24T11:10:36.000Z", "time": 11869}, {"rank": 142, "name": "ecsplos1v", "date": "2014-01-09T20:58:00.000Z", "time": 11896}, {"rank": 143, "name": "jaylez", "date": "2014-06-01T14:47:00.000Z", "time": 12031}, {"rank": 144, "name": "ChewMyFudge", "date": "2014-01-30T18:13:00.000Z", "time": 12048}, {"rank": 145, "name": "Yeppa2s", "date": "2014-07-06T16:26:21.000Z", "time": 12076}, {"rank": 146, "name": "meitze", "date": "2014-03-06T11:21:00.000Z", "time": 12089}, {"rank": 147, "name": "lvnte", "date": "2013-12-22T23:39:00.000Z", "time": 12134}, {"rank": 148, "name": "rethrow", "date": "2014-04-20T08:08:00.000Z", "time": 12149}, {"rank": 149, "name": "devKev", "date": "2014-04-12T11:48:00.000Z", "time": 12153}, {"rank": 150, "name": "xtraterrestrial", "date": "2014-06-09T07:51:57.000Z", "time": 12175}, {"rank": 151, "name": "gamawsta4", "date": "2013-12-28T14:23:00.000Z", "time": 12190}, {"rank": 152, "name": "MauZZR", "date": "2013-12-27T17:07:00.000Z", "time": 12208}, {"rank": 153, "name": "cool_breeze", "date": "2014-02-08T09:39:00.000Z", "time": 12323}, {"rank": 154, "name": "rejZa", "date": "2014-08-14T16:30:55.000Z", "time": 12332}, {"rank": 155, "name": "BeZedAsh", "date": "2014-06-25T19:15:30.000Z", "time": 12397}, {"rank": 156, "name": "Protone", "date": "2014-03-06T11:21:00.000Z", "time": 12449}, {"rank": 157, "name": "QuakeBro", "date": "2014-08-06T07:25:09.000Z", "time": 12474}, {"rank": 158, "name": "n3w_", "date": "2014-06-01T06:25:00.000Z", "time": 12555}, {"rank": 159, "name": "Garchomp", "date": "2014-01-28T10:00:00.000Z", "time": 12569}, {"rank": 160, "name": "wormskull", "date": "2014-04-28T01:03:30.000Z", "time": 12594}, {"rank": 161, "name": "Taffy_", "date": "2014-02-08T09:39:00.000Z", "time": 12597}, {"rank": 162, "name": "BooM3r14", "date": "2014-07-09T13:27:52.000Z", "time": 12649}, {"rank": 163, "name": "Mcay", "date": "2014-02-10T05:18:00.000Z", "time": 12683}, {"rank": 164, "name": "Smokey_J_McPot", "date": "2014-08-26T00:48:00.000Z", "time": 12743}, {"rank": 165, "name": "ventzer", "date": "2014-03-26T19:26:00.000Z", "time": 12774}, {"rank": 166, "name": "LidlWayne", "date": "2014-08-05T17:37:19.000Z", "time": 12804}, {"rank": 167, "name": "pr00te", "date": "2013-11-26T12:50:00.000Z", "time": 12815}, {"rank": 168, "name": "No_Aim_here", "date": "2014-08-19T21:49:00.000Z", "time": 12918}, {"rank": 169, "name": "NonSwiMmerz", "date": "2014-02-13T05:18:00.000Z", "time": 12966}, {"rank": 170, "name": "mlgward", "date": "2014-07-06T20:15:15.000Z", "time": 13104}, {"rank": 171, "name": "Fuldas", "date": "2014-06-18T13:04:42.000Z", "time": 13111}, {"rank": 172, "name": "GibiskUss", "date": "2014-02-19T17:31:00.000Z", "time": 13209}, {"rank": 173, "name": "Asuka_", "date": "2014-04-11T23:52:00.000Z", "time": 13292}, {"rank": 174, "name": "Nutcase", "date": "2014-07-06T20:15:15.000Z", "time": 13294}, {"rank": 175, "name": "i5eeCZE", "date": "2014-08-22T07:24:38.000Z", "time": 13417}, {"rank": 176, "name": "MarBoJIIIIe6Huk", "date": "2014-08-06T08:10:16.000Z", "time": 13429}, {"rank": 177, "name": "MayanMayo", "date": "2014-04-12T11:48:00.000Z", "time": 13441}, {"rank": 178, "name": "yutti", "date": "2014-03-12T03:58:00.000Z", "time": 13471}, {"rank": 179, "name": "Gabe_Ramsay", "date": "2014-02-16T02:51:00.000Z", "time": 13492}, {"rank": 180, "name": "PythonAsp", "date": "2013-12-18T11:42:00.000Z", "time": 13498}, {"rank": 181, "name": "Uhuru", "date": "2014-08-17T20:49:15.000Z", "time": 13509}, {"rank": 182, "name": "Squaxx", "date": "2013-11-29T09:58:00.000Z", "time": 13543}, {"rank": 183, "name": "Giants", "date": "2014-07-01T23:42:40.000Z", "time": 13574}, {"rank": 184, "name": "edniM", "date": "2014-05-18T13:43:05.000Z", "time": 13619}, {"rank": 185, "name": "Kupez32", "date": "2014-08-26T18:38:59.000Z", "time": 13620}, {"rank": 186, "name": "ACow", "date": "2014-06-09T00:38:09.000Z", "time": 13651}, {"rank": 187, "name": "Lamidex", "date": "2014-08-10T11:39:49.000Z", "time": 13766}, {"rank": 188, "name": "Kiv_vi", "date": "2014-06-09T15:09:53.000Z", "time": 13825}, {"rank": 189, "name": "pupupipa", "date": "2014-02-25T16:39:00.000Z", "time": 13832}, {"rank": 190, "name": "Aeph", "date": "2014-03-01T03:00:00.000Z", "time": 13833}, {"rank": 191, "name": "AnalFury", "date": "2014-07-05T02:17:31.000Z", "time": 13841}, {"rank": 192, "name": "Cyller", "date": "2014-05-29T16:36:00.000Z", "time": 13897}, {"rank": 193, "name": "Scythe554", "date": "2014-06-01T06:25:00.000Z", "time": 13971}, {"rank": 194, "name": "Legendah", "date": "2014-02-21T05:24:00.000Z", "time": 13975}, {"rank": 195, "name": "andrasrx8", "date": "2014-08-06T19:51:41.000Z", "time": 14061}, {"rank": 196, "name": "dEElan", "date": "2014-08-24T10:24:32.000Z", "time": 14062}, {"rank": 197, "name": "Danlan5", "date": "2014-08-17T18:24:29.000Z", "time": 14143}, {"rank": 198, "name": "Borma", "date": "2014-05-24T02:56:26.000Z", "time": 14173}, {"rank": 199, "name": "jibimas", "date": "2014-07-09T13:27:52.000Z", "time": 14319}, {"rank": 200, "name": "MaxiBooM", "date": "2014-08-24T11:10:36.000Z", "time": 14442}, {"rank": 201, "name": "EleTrIK", "date": "2014-02-13T05:18:00.000Z", "time": 14446}, {"rank": 202, "name": "titatixas", "date": "2014-08-18T19:05:54.000Z", "time": 14470}, {"rank": 203, "name": "Ammaccabanane", "date": "2013-12-24T08:37:00.000Z", "time": 14542}, {"rank": 204, "name": "iov", "date": "2014-05-18T13:43:05.000Z", "time": 14562}, {"rank": 205, "name": "Gisbourne", "date": "2014-05-18T13:43:05.000Z", "time": 14563}, {"rank": 206, "name": "flug3r", "date": "2014-04-13T14:40:00.000Z", "time": 14568}, {"rank": 207, "name": "laachss", "date": "2014-01-12T12:02:00.000Z", "time": 14591}, {"rank": 208, "name": "Her0c", "date": "2014-08-06T08:10:16.000Z", "time": 14599}, {"rank": 209, "name": "MrBeefcake", "date": "2014-04-20T08:08:00.000Z", "time": 14603}, {"rank": 210, "name": "Mietek_Zul", "date": "2014-06-14T00:52:30.000Z", "time": 14608}, {"rank": 211, "name": "emilie", "date": "2014-08-11T02:45:56.000Z", "time": 14704}, {"rank": 212, "name": "Schuder", "date": "2014-07-05T02:01:57.000Z", "time": 14709}, {"rank": 213, "name": "CMSS", "date": "2014-01-28T10:00:00.000Z", "time": 14791}, {"rank": 214, "name": "Cobr4", "date": "2013-11-17T07:44:00.000Z", "time": 14825}, {"rank": 215, "name": "SoAoG", "date": "2013-12-18T11:42:00.000Z", "time": 14860}, {"rank": 216, "name": "the_devil", "date": "2014-06-14T00:52:30.000Z", "time": 14950}, {"rank": 217, "name": "OneRepubiic", "date": "2014-05-29T16:36:00.000Z", "time": 14978}, {"rank": 218, "name": "YaCoU", "date": "2013-12-04T11:02:00.000Z", "time": 15118}, {"rank": 219, "name": "Brancaleone", "date": "2013-12-24T08:37:00.000Z", "time": 15120}, {"rank": 220, "name": "chepe51", "date": "2014-04-13T14:39:00.000Z", "time": 15207}, {"rank": 221, "name": "KillerReplayZ", "date": "2014-08-26T00:48:00.000Z", "time": 15211}, {"rank": 222, "name": "Duckangelito", "date": "2014-06-28T02:48:13.000Z", "time": 15250}, {"rank": 223, "name": "VinuJ", "date": "2014-08-07T16:31:02.000Z", "time": 15272}, {"rank": 224, "name": "KyleBond", "date": "2014-04-09T17:05:00.000Z", "time": 15325}, {"rank": 225, "name": "DrtyPop", "date": "2014-08-20T06:09:48.000Z", "time": 15336}, {"rank": 226, "name": "xMurrsielagox", "date": "2014-05-18T13:52:06.000Z", "time": 15351}, {"rank": 227, "name": "xCygnus", "date": "2014-01-05T19:37:00.000Z", "time": 15389}, {"rank": 228, "name": "vS1", "date": "2014-02-22T13:36:00.000Z", "time": 15400}, {"rank": 229, "name": "mcgamingkiddo", "date": "2014-04-07T07:48:00.000Z", "time": 15497}, {"rank": 230, "name": "vlad26", "date": "2014-04-07T07:48:00.000Z", "time": 15517}, {"rank": 231, "name": "L4zyGuy", "date": "2014-07-06T20:05:33.000Z", "time": 15668}, {"rank": 232, "name": "MistrzYoda", "date": "2013-12-03T04:21:00.000Z", "time": 15716}, {"rank": 233, "name": "quickiquakkel", "date": "2014-08-24T10:24:32.000Z", "time": 15724}, {"rank": 234, "name": "pawelmar1212", "date": "2014-04-20T08:08:00.000Z", "time": 15880}, {"rank": 235, "name": "tunk", "date": "2014-04-22T08:30:00.000Z", "time": 15892}, {"rank": 236, "name": "MedievalManIII", "date": "2014-04-22T08:30:00.000Z", "time": 16024}, {"rank": 237, "name": "Tryton", "date": "2014-08-06T19:51:41.000Z", "time": 16145}, {"rank": 238, "name": "Slafz", "date": "2014-01-28T10:00:00.000Z", "time": 16276}, {"rank": 239, "name": "nviime", "date": "2014-07-01T23:42:40.000Z", "time": 16368}, {"rank": 240, "name": "fatface", "date": "2014-04-09T17:05:00.000Z", "time": 16383}, {"rank": 241, "name": "Zed_451", "date": "2014-04-16T13:28:00.000Z", "time": 16471}, {"rank": 242, "name": "boogiepop", "date": "2014-01-10T08:59:00.000Z", "time": 16513}, {"rank": 243, "name": "Geova", "date": "2014-07-05T02:01:57.000Z", "time": 16563}, {"rank": 244, "name": "Alithinos", "date": "2014-07-06T20:15:15.000Z", "time": 16631}, {"rank": 245, "name": "PiccoloDik", "date": "2014-08-11T02:45:56.000Z", "time": 16796}, {"rank": 246, "name": "mcSim", "date": "2014-03-02T00:27:00.000Z", "time": 16854}, {"rank": 247, "name": "ToxiKK", "date": "2014-07-28T20:31:16.000Z", "time": 16886}, {"rank": 248, "name": "Screach", "date": "2014-04-20T08:08:00.000Z", "time": 16998}, {"rank": 249, "name": "_EL3TRiC_GAM3R_", "date": "2014-04-07T07:48:00.000Z", "time": 17097}, {"rank": 250, "name": "sossos", "date": "2014-08-07T16:31:02.000Z", "time": 17123}, {"rank": 251, "name": "IUSECAPSLOCK", "date": "2014-07-06T16:26:21.000Z", "time": 17135}, {"rank": 252, "name": "JAN0MAIDENMETAL", "date": "2014-05-29T16:36:00.000Z", "time": 17149}, {"rank": 253, "name": "Wykalaczka", "date": "2013-12-02T01:08:00.000Z", "time": 17217}, {"rank": 254, "name": "AriSphinX", "date": "2014-05-24T02:56:26.000Z", "time": 17248}, {"rank": 255, "name": "j2ko", "date": "2014-04-24T23:11:00.000Z", "time": 17264}, {"rank": 256, "name": "spiky3311", "date": "2013-12-04T11:02:00.000Z", "time": 17297}, {"rank": 257, "name": "zLo1berG", "date": "2014-08-19T21:49:00.000Z", "time": 17302}, {"rank": 258, "name": "brewmaster_LnX", "date": "2014-08-06T17:25:46.000Z", "time": 17320}, {"rank": 259, "name": "__annaveleria__", "date": "2014-03-06T10:19:00.000Z", "time": 17327}, {"rank": 260, "name": "monstriukas", "date": "2014-04-07T07:38:00.000Z", "time": 17330}, {"rank": 261, "name": "Yeroxy", "date": "2014-08-07T03:55:53.000Z", "time": 17687}, {"rank": 262, "name": "Dexter_", "date": "2014-08-14T20:06:34.000Z", "time": 17867}, {"rank": 263, "name": "limp", "date": "2013-11-17T07:44:00.000Z", "time": 17876}, {"rank": 264, "name": "Zlash888", "date": "2013-11-21T15:06:00.000Z", "time": 17979}, {"rank": 265, "name": "mitulbharti", "date": "2014-07-06T16:26:21.000Z", "time": 18007}, {"rank": 266, "name": "Saver", "date": "2014-07-09T13:27:52.000Z", "time": 18052}, {"rank": 267, "name": "C4GE", "date": "2014-08-08T03:07:06.000Z", "time": 18059}, {"rank": 268, "name": "Yep", "date": "2014-03-02T00:27:00.000Z", "time": 18069}, {"rank": 269, "name": "samok86", "date": "2014-03-05T22:41:00.000Z", "time": 18191}, {"rank": 270, "name": "Vaions", "date": "2014-05-29T16:36:00.000Z", "time": 18279}, {"rank": 271, "name": "warp_", "date": "2014-08-06T02:55:48.000Z", "time": 18630}, {"rank": 272, "name": "pelat", "date": "2014-06-09T00:38:09.000Z", "time": 18668}, {"rank": 273, "name": "oz90", "date": "2014-08-14T11:26:19.000Z", "time": 18717}, {"rank": 274, "name": "need2killcl", "date": "2013-11-18T14:04:00.000Z", "time": 18842}, {"rank": 275, "name": "Gesspar", "date": "2013-11-26T12:50:00.000Z", "time": 18990}, {"rank": 276, "name": "kodisha", "date": "2014-02-21T05:24:00.000Z", "time": 19094}, {"rank": 277, "name": "woolwoos", "date": "2014-08-14T17:14:56.000Z", "time": 19154}, {"rank": 278, "name": "frieda_02", "date": "2014-04-07T07:38:00.000Z", "time": 19682}, {"rank": 279, "name": "WiiMand", "date": "2013-11-26T12:50:00.000Z", "time": 19825}, {"rank": 280, "name": "scrotedogg99", "date": "2014-04-28T01:03:30.000Z", "time": 19857}, {"rank": 281, "name": "Sahido", "date": "2014-08-14T11:26:19.000Z", "time": 19874}, {"rank": 282, "name": "SoDIceCow", "date": "2014-04-07T07:48:00.000Z", "time": 20167}, {"rank": 283, "name": "ElmoAsassin78", "date": "2014-06-06T02:12:18.000Z", "time": 20520}, {"rank": 284, "name": "tiggynikka", "date": "2014-06-18T13:04:42.000Z", "time": 20768}, {"rank": 285, "name": "YumiikOoO", "date": "2014-08-06T08:10:16.000Z", "time": 20815}, {"rank": 286, "name": "miklas_ostereje", "date": "2014-04-20T08:08:00.000Z", "time": 20821}, {"rank": 287, "name": "Houssy", "date": "2014-06-02T00:52:00.000Z", "time": 21055}, {"rank": 288, "name": "ruchirbharti", "date": "2014-08-07T14:49:28.000Z", "time": 21243}, {"rank": 289, "name": "cb1", "date": "2014-08-17T18:24:29.000Z", "time": 21257}, {"rank": 290, "name": "WarDeV1L", "date": "2014-07-09T13:27:52.000Z", "time": 21514}, {"rank": 291, "name": "VisitingBoss", "date": "2014-02-24T10:42:00.000Z", "time": 21607}, {"rank": 292, "name": "julietteb85", "date": "2014-07-09T13:27:52.000Z", "time": 21614}, {"rank": 293, "name": "StVicious", "date": "2014-06-18T13:04:42.000Z", "time": 21681}, {"rank": 294, "name": "Zholotoi", "date": "2014-04-07T07:48:00.000Z", "time": 22525}, {"rank": 295, "name": "Skwizgar", "date": "2014-04-07T07:38:00.000Z", "time": 22627}, {"rank": 296, "name": "Luminus", "date": "2014-04-24T23:11:00.000Z", "time": 23192}, {"rank": 297, "name": "gemacheck", "date": "2014-04-20T08:08:00.000Z", "time": 23975}, {"rank": 298, "name": "hidj", "date": "2014-06-06T02:12:18.000Z", "time": 24193}, {"rank": 299, "name": "Wargud", "date": "2014-08-17T18:24:29.000Z", "time": 24847}, {"rank": 300, "name": "11vovchik2004", "date": "2014-04-27T12:18:24.000Z", "time": 26433}, {"rank": 301, "name": "Pe_mpas_freak23", "date": "2014-08-06T07:25:09.000Z", "time": 29654}, {"rank": 302, "name": "mar420", "date": "2014-04-27T12:18:24.000Z", "time": 32063}, {"rank": 303, "name": "JordanB", "date": "2014-03-26T19:26:00.000Z", "time": 40232}, {"rank": 304, "name": "Nestor01", "date": "2014-07-06T16:26:21.000Z", "time": 42867}, {"rank": 305, "name": "sTaTiiC_BlaDeZ", "date": "2014-08-14T14:42:30.000Z", "time": 45295}, {"rank": 306, "name": "raekw0n", "date": "2014-08-06T17:25:46.000Z", "time": 55515}]}