{"records": [{"rank": 1, "name": "Nightmare", "date": "2015-05-17T06:45:07.000Z", "time": 6869}, {"rank": 2, "name": "pentagramBurns", "date": "2015-02-08T22:37:14.000Z", "time": 7003}, {"rank": 3, "name": "Exkalibur", "date": "2015-02-08T22:37:14.000Z", "time": 7041}, {"rank": 4, "name": "d3lt4_07", "date": "2015-05-16T23:47:50.000Z", "time": 7159}, {"rank": 5, "name": "kanzo", "date": "2015-01-31T19:14:04.000Z", "time": 7374}, {"rank": 6, "name": "frixio", "date": "2014-09-20T17:14:58.000Z", "time": 7458}, {"rank": 7, "name": "Lakitu", "date": "2015-02-08T22:15:09.000Z", "time": 7470}, {"rank": 8, "name": "w_w", "date": "2015-02-08T18:30:46.000Z", "time": 7522}, {"rank": 9, "name": "FuXiarz", "date": "2015-01-11T21:17:26.000Z", "time": 7525}, {"rank": 10, "name": "Dezerter", "date": "2015-05-03T10:23:17.000Z", "time": 7534}, {"rank": 11, "name": "benje", "date": "2015-05-30T22:47:23.000Z", "time": 7563}, {"rank": 12, "name": "Quebo", "date": "2015-10-10T10:31:12.000Z", "time": 7596}, {"rank": 13, "name": "cast", "date": "2015-01-31T19:14:04.000Z", "time": 7635}, {"rank": 14, "name": "Personal_Best", "date": "2015-05-03T17:21:54.000Z", "time": 7691}, {"rank": 15, "name": "xXApathyXx", "date": "2015-03-04T23:16:33.000Z", "time": 7694}, {"rank": 16, "name": "5hr00m", "date": "2015-02-16T17:30:16.000Z", "time": 7699}, {"rank": 17, "name": "paparas", "date": "2015-08-27T18:11:20.000Z", "time": 7701}, {"rank": 18, "name": "TheItalianGuy", "date": "2015-02-21T10:36:14.000Z", "time": 7775}, {"rank": 19, "name": "e1348391", "date": "2015-08-02T07:19:42.000Z", "time": 7808}, {"rank": 20, "name": "QuakeThreshold", "date": "2014-07-16T01:32:18.000Z", "time": 7812}, {"rank": 21, "name": "P_D", "date": "2015-02-02T11:33:20.000Z", "time": 7841}, {"rank": 22, "name": "takkomatto", "date": "2015-02-10T07:49:26.000Z", "time": 8008}, {"rank": 23, "name": "MicFragger", "date": "2015-09-10T14:05:42.000Z", "time": 8231}, {"rank": 24, "name": "wouternero", "date": "2015-02-21T15:13:41.000Z", "time": 8455}, {"rank": 25, "name": "DieselPower_Kr", "date": "2015-08-31T05:32:54.000Z", "time": 8463}, {"rank": 26, "name": "Drizztman", "date": "2015-02-01T16:01:57.000Z", "time": 8471}, {"rank": 27, "name": "PlayDooM", "date": "2015-03-15T12:27:15.000Z", "time": 8873}, {"rank": 28, "name": "muckster", "date": "2014-07-10T10:55:38.000Z", "time": 9033}, {"rank": 29, "name": "nldex", "date": "2014-09-26T20:16:08.000Z", "time": 9164}, {"rank": 30, "name": "Her0c", "date": "2015-07-31T12:41:32.000Z", "time": 9284}, {"rank": 31, "name": "segre", "date": "2015-03-03T23:06:44.000Z", "time": 9383}, {"rank": 32, "name": "FlyingOrodrake", "date": "2014-08-23T12:44:37.000Z", "time": 9392}, {"rank": 33, "name": "Gnampf", "date": "2014-07-17T12:14:55.000Z", "time": 9741}, {"rank": 34, "name": "xtsy", "date": "2014-09-02T03:53:04.000Z", "time": 9841}, {"rank": 35, "name": "suppengabel", "date": "2015-10-10T10:31:12.000Z", "time": 10049}, {"rank": 36, "name": "freemotioncopy", "date": "2015-08-24T20:04:37.000Z", "time": 10051}, {"rank": 37, "name": "xSkizShadow", "date": "2015-05-02T21:17:09.000Z", "time": 10355}, {"rank": 38, "name": "bula1", "date": "2015-08-21T19:42:19.000Z", "time": 10500}, {"rank": 39, "name": "Lamidex", "date": "2014-08-17T17:23:47.000Z", "time": 12015}, {"rank": 40, "name": "PowerofTruth", "date": "2014-07-30T23:28:41.000Z", "time": 12141}, {"rank": 41, "name": "Sov137", "date": "2015-04-14T02:37:33.000Z", "time": 14624}, {"rank": 42, "name": "He63D9lLLjuu", "date": "2014-09-20T19:50:35.000Z", "time": 16421}, {"rank": 43, "name": "BEIPE1", "date": "2015-10-02T05:19:45.000Z", "time": 19285}, {"rank": 44, "name": "marin3", "date": "2014-08-23T03:23:26.000Z", "time": 19516}, {"rank": 45, "name": "Karm", "date": "2014-09-26T20:16:08.000Z", "time": 21126}, {"rank": 46, "name": "CleanUpGuy", "date": "2014-08-06T06:32:29.000Z", "time": 21358}, {"rank": 47, "name": "fingalius", "date": "2015-09-18T05:01:42.000Z", "time": 23564}, {"rank": 48, "name": "bogotify", "date": "2014-08-09T05:04:34.000Z", "time": 23724}, {"rank": 49, "name": "JuJitSoup", "date": "2014-09-25T16:09:03.000Z", "time": 24041}, {"rank": 50, "name": "tenacious_g", "date": "2015-02-08T18:30:46.000Z", "time": 27342}, {"rank": 51, "name": "zombies972", "date": "2014-10-13T23:52:52.000Z", "time": 28955}, {"rank": 52, "name": "Sergei_Ghost", "date": "2014-10-04T04:32:39.000Z", "time": 39481}]}